[
  {
    "position": {
      "x": 556.0057293555699,
      "y": -102.55061731176556,
      "z": 134.7965954203711
    },
    "rotation": {
      "x": 0,
      "y": 1.4824500000625864,
      "z": 0
    },
    "scale": {
      "x": 1,
      "y": 1,
      "z": 1
    }
  },
  {
    "position": {
      "x": 542.3093543430034,
      "y": -101.35535771887689,
      "z": 133.58341302899544
    },
    "rotation": {
      "x": 0,
      "y": 1.4824500000625864,
      "z": 0
    },
    "scale": {
      "x": 1,
      "y": 1,
      "z": 1
    }
  },
  {
    "position": {
      "x": 530.0671564090399,
      "y": -99.96776161439817,
      "z": 131.24181653746712
    },
    "rotation": {
      "x": 0,
      "y": 1.3452000000625866,
      "z": 0
    },
    "scale": {
      "x": 1,
      "y": 1,
      "z": 1
    }
  },
  {
    "position": {
      "x": 513.1827717888018,
      "y": -96.89214629658233,
      "z": 123.44969463735663
    },
    "rotation": {
      "x": 0,
      "y": 0.957300000026824,
      "z": 0
    },
    "scale": {
      "x": 1,
      "y": 1,
      "z": 1
    }
  },
  {
    "position": {
      "x": 504.32772971958116,
      "y": -94.73216905121458,
      "z": 117.21454187694553
    },
    "rotation": {
      "x": 0,
      "y": 0.957300000026824,
      "z": 0
    },
    "scale": {
      "x": 1,
      "y": 1,
      "z": 1
    }
  },
  {
    "position": {
      "x": 491.79389651045904,
      "y": -91.47183772348308,
      "z": 107.59160532747535
    },
    "rotation": {
      "x": 0,
      "y": 0.8701500000357647,
      "z": 0
    },
    "scale": {
      "x": 1,
      "y": 1,
      "z": 1
    }
  },
  {
    "position": {
      "x": 471.40097148215136,
      "y": -86.32399609721284,
      "z": 91.81956844592969
    },
    "rotation": {
      "x": 0,
      "y": 1.0203000000268239,
      "z": 0
    },
    "scale": {
      "x": 1,
      "y": 1,
      "z": 1
    }
  },
  {
    "position": {
      "x": 461.43799371005457,
      "y": -83.53776014891687,
      "z": 85.70440909462968
    },
    "rotation": {
      "x": 0,
      "y": 1.0203000000268239,
      "z": 0
    },
    "scale": {
      "x": 1,
      "y": 1,
      "z": 1
    }
  },
  {
    "position": {
      "x": 452.2292704553395,
      "y": -80.95900657654656,
      "z": 80.05220235355637
    },
    "rotation": {
      "x": 0,
      "y": 1.0203000000268239,
      "z": 0
    },
    "scale": {
      "x": 1,
      "y": 1,
      "z": 1
    }
  },
  {
    "position": {
      "x": 441.21800674161386,
      "y": -77.81247564553493,
      "z": 73.29361733922315
    },
    "rotation": {
      "x": 0,
      "y": 1.0203000000268239,
      "z": 0
    },
    "scale": {
      "x": 1,
      "y": 1,
      "z": 1
    }
  },
  {
    "position": {
      "x": 426.5933941082217,
      "y": -73.64780676484088,
      "z": 63.68191131351023
    },
    "rotation": {
      "x": 0,
      "y": 0.9712500000447052,
      "z": 0
    },
    "scale": {
      "x": 1,
      "y": 1,
      "z": 1
    }
  },
  {
    "position": {
      "x": 415.2373207483827,
      "y": -70.12078842868686,
      "z": 55.262231151351216
    },
    "rotation": {
      "x": 0,
      "y": 0.8466000000536459,
      "z": 0
    },
    "scale": {
      "x": 1,
      "y": 1,
      "z": 1
    }
  },
  {
    "position": {
      "x": 405.7309648148307,
      "y": -66.74930068533098,
      "z": 46.54517465135018
    },
    "rotation": {
      "x": 0,
      "y": 0.7224000000357644,
      "z": 0
    },
    "scale": {
      "x": 1,
      "y": 1,
      "z": 1
    }
  },
  {
    "position": {
      "x": 399.1518269239534,
      "y": -64.0822591162243,
      "z": 38.5108708293385
    },
    "rotation": {
      "x": 0,
      "y": 0.6456000000536458,
      "z": 0
    },
    "scale": {
      "x": 1,
      "y": 1,
      "z": 1
    }
  },
  {
    "position": {
      "x": 393.31598375662884,
      "y": -61.22044877544582,
      "z": 29.445368038607285
    },
    "rotation": {
      "x": 0,
      "y": 0.5586000000536457,
      "z": 0
    },
    "scale": {
      "x": 1,
      "y": 1,
      "z": 1
    }
  },
  {
    "position": {
      "x": 387.943300921424,
      "y": -57.94782528345573,
      "z": 18.712116170083846
    },
    "rotation": {
      "x": 0,
      "y": 0.4213500000536458,
      "z": 0
    },
    "scale": {
      "x": 1,
      "y": 1,
      "z": 1
    }
  },
  {
    "position": {
      "x": 384.84623555731855,
      "y": -55.46411163137944,
      "z": 9.70518692155565
    },
    "rotation": {
      "x": 0,
      "y": 0.28200000004470516,
      "z": 0
    },
    "scale": {
      "x": 1,
      "y": 1,
      "z": 1
    }
  },
  {
    "position": {
      "x": 383.0912881187194,
      "y": -53.29274810035355,
      "z": 1.1583202925810383
    },
    "rotation": {
      "x": 0,
      "y": 0.18030000007152727,
      "z": 0
    },
    "scale": {
      "x": 1,
      "y": 1,
      "z": 1
    }
  },
  {
    "position": {
      "x": 380.9913956646833,
      "y": -50.396230809312556,
      "z": -10.361859899920319
    },
    "rotation": {
      "x": 0,
      "y": 0.18030000007152727,
      "z": 0
    },
    "scale": {
      "x": 1,
      "y": 1,
      "z": 1
    }
  },
  {
    "position": {
      "x": 379.0043209426317,
      "y": -47.52705149208276,
      "z": -21.439639808977518
    },
    "rotation": {
      "x": 0,
      "y": 0.12990000008046798,
      "z": 0
    },
    "scale": {
      "x": 1,
      "y": 1,
      "z": 1
    }
  },
  {
    "position": {
      "x": 378.4648170976652,
      "y": -45.31087225275655,
      "z": -30.545413559339522
    },
    "rotation": {
      "x": 0,
      "y": 0.04365000008046799,
      "z": 0
    },
    "scale": {
      "x": 1,
      "y": 1,
      "z": 1
    }
  },
  {
    "position": {
      "x": 377.96867418380884,
      "y": -42.63886182739324,
      "z": -41.9045835209165
    },
    "rotation": {
      "x": 0,
      "y": 0.04365000008046799,
      "z": 0
    },
    "scale": {
      "x": 1,
      "y": 1,
      "z": 1
    }
  },
  {
    "position": {
      "x": 378.6313968872355,
      "y": -40.049785408759305,
      "z": -53.426323796006955
    },
    "rotation": {
      "x": 0,
      "y": -0.08294999988376923,
      "z": 0
    },
    "scale": {
      "x": 1,
      "y": 1,
      "z": 1
    }
  },
  {
    "position": {
      "x": 380.9237889272042,
      "y": -37.49656111022213,
      "z": -65.3789318759957
    },
    "rotation": {
      "x": 0,
      "y": -0.24554999989270995,
      "z": 0
    },
    "scale": {
      "x": 1,
      "y": 1,
      "z": 1
    }
  },
  {
    "position": {
      "x": 383.9466113800395,
      "y": -34.9012197159816,
      "z": -77.44092878534252
    },
    "rotation": {
      "x": 0,
      "y": -0.25844999988376927,
      "z": 0
    },
    "scale": {
      "x": 1,
      "y": 1,
      "z": 1
    }
  },
  {
    "position": {
      "x": 388.2314793342621,
      "y": -32.81816085597865,
      "z": -88.32305973635039
    },
    "rotation": {
      "x": 0,
      "y": -0.4109999998658878,
      "z": 0
    },
    "scale": {
      "x": 1,
      "y": 1,
      "z": 1
    }
  },
  {
    "position": {
      "x": 393.5374749422497,
      "y": -31.07012884998892,
      "z": -98.18068833144707
    },
    "rotation": {
      "x": 0,
      "y": -0.5386499998569471,
      "z": 0
    },
    "scale": {
      "x": 1,
      "y": 1,
      "z": 1
    }
  },
  {
    "position": {
      "x": 400.61022842443276,
      "y": -29.608590922541794,
      "z": -107.49884648285456
    },
    "rotation": {
      "x": 0,
      "y": -0.7007999998480066,
      "z": 0
    },
    "scale": {
      "x": 1,
      "y": 1,
      "z": 1
    }
  },
  {
    "position": {
      "x": 408.0025143062617,
      "y": -28.431343484906336,
      "z": -115.45343605238918
    },
    "rotation": {
      "x": 0,
      "y": -0.7754999998211844,
      "z": 0
    },
    "scale": {
      "x": 1,
      "y": 1,
      "z": 1
    }
  },
  {
    "position": {
      "x": 417.08427052337424,
      "y": -27.424264586282106,
      "z": -123.25009098996725
    },
    "rotation": {
      "x": 0,
      "y": -0.9028499997854216,
      "z": 0
    },
    "scale": {
      "x": 1,
      "y": 1,
      "z": 1
    }
  },
  {
    "position": {
      "x": 426.65275766501213,
      "y": -26.884853378034393,
      "z": -129.087215454819
    },
    "rotation": {
      "x": 0,
      "y": -1.0651499998122438,
      "z": 0
    },
    "scale": {
      "x": 1,
      "y": 1,
      "z": 1
    }
  },
  {
    "position": {
      "x": 438.2091718615982,
      "y": -26.40877810354698,
      "z": -134.8741705251541
    },
    "rotation": {
      "x": 0,
      "y": -1.1650499998033035,
      "z": 0
    },
    "scale": {
      "x": 1,
      "y": 1,
      "z": 1
    }
  },
  {
    "position": {
      "x": 448.1401323979526,
      "y": -26.44745900882458,
      "z": -137.9595226784179
    },
    "rotation": {
      "x": 0,
      "y": -1.311299999803303,
      "z": 0
    },
    "scale": {
      "x": 1,
      "y": 1,
      "z": 1
    }
  },
  {
    "position": {
      "x": 456.69213508431403,
      "y": -26.770184018300768,
      "z": -139.39645098173287
    },
    "rotation": {
      "x": 0,
      "y": -1.4384999998211847,
      "z": 0
    },
    "scale": {
      "x": 1,
      "y": 1,
      "z": 1
    }
  },
  {
    "position": {
      "x": 469.16371563746657,
      "y": -27.767360056377584,
      "z": -139.73405649897086
    },
    "rotation": {
      "x": 0,
      "y": -1.5881999997943628,
      "z": 0
    },
    "scale": {
      "x": 1,
      "y": 1,
      "z": 1
    }
  },
  {
    "position": {
      "x": 480.7507139462514,
      "y": -29.195977077909617,
      "z": -138.27393222567048
    },
    "rotation": {
      "x": 0,
      "y": -1.7254499997943629,
      "z": 0
    },
    "scale": {
      "x": 1,
      "y": 1,
      "z": 1
    }
  },
  {
    "position": {
      "x": 506.54754918906315,
      "y": -32.76074396145833,
      "z": -131.68849775480498
    },
    "rotation": {
      "x": 0,
      "y": -1.8361499997675406,
      "z": 0
    },
    "scale": {
      "x": 1,
      "y": 1,
      "z": 1
    }
  },
  {
    "position": {
      "x": 518.2143968961075,
      "y": -34.339267807125054,
      "z": -128.51788825580843
    },
    "rotation": {
      "x": 0,
      "y": -1.8361499997675406,
      "z": 0
    },
    "scale": {
      "x": 1,
      "y": 1,
      "z": 1
    }
  },
  {
    "position": {
      "x": 529.7624622560229,
      "y": -36.040788113090855,
      "z": -124.7342541693954
    },
    "rotation": {
      "x": 0,
      "y": -1.9990499997585998,
      "z": 0
    },
    "scale": {
      "x": 1,
      "y": 1,
      "z": 1
    }
  },
  {
    "position": {
      "x": 539.8913301099572,
      "y": -38.1252667130874,
      "z": -119.02880129523624
    },
    "rotation": {
      "x": 0,
      "y": -2.1743999997675396,
      "z": 0
    },
    "scale": {
      "x": 1,
      "y": 1,
      "z": 1
    }
  },
  {
    "position": {
      "x": 549.1451712303037,
      "y": -40.33604116401315,
      "z": -112.64883072325892
    },
    "rotation": {
      "x": 0,
      "y": -2.1743999997675396,
      "z": 0
    },
    "scale": {
      "x": 1,
      "y": 1,
      "z": 1
    }
  },
  {
    "position": {
      "x": 558.5839217853725,
      "y": -42.62966098620464,
      "z": -105.92263377371432
    },
    "rotation": {
      "x": 0,
      "y": -2.2847999997585986,
      "z": 0
    },
    "scale": {
      "x": 1,
      "y": 1,
      "z": 1
    }
  },
  {
    "position": {
      "x": 565.7434395784126,
      "y": -45.0090216917676,
      "z": -98.37746201541245
    },
    "rotation": {
      "x": 0,
      "y": -2.4100499997585985,
      "z": 0
    },
    "scale": {
      "x": 1,
      "y": 1,
      "z": 1
    }
  },
  {
    "position": {
      "x": 573.2653266178102,
      "y": -47.62301483867222,
      "z": -89.9983919385445
    },
    "rotation": {
      "x": 0,
      "y": -2.4100499997585985,
      "z": 0
    },
    "scale": {
      "x": 1,
      "y": 1,
      "z": 1
    }
  },
  {
    "position": {
      "x": 582.7175821210658,
      "y": -51.55220996503974,
      "z": -76.80262469672061
    },
    "rotation": {
      "x": 0,
      "y": -2.5484999997764803,
      "z": 0
    },
    "scale": {
      "x": 1,
      "y": 1,
      "z": 1
    }
  },
  {
    "position": {
      "x": 588.8370839668123,
      "y": -54.80689402434808,
      "z": -65.40904588431204
    },
    "rotation": {
      "x": 0,
      "y": -2.7128999998122434,
      "z": 0
    },
    "scale": {
      "x": 1,
      "y": 1,
      "z": 1
    }
  },
  {
    "position": {
      "x": 592.5651950616955,
      "y": -57.61946023251585,
      "z": -55.261567919227446
    },
    "rotation": {
      "x": 0,
      "y": -2.8502999998033025,
      "z": 0
    },
    "scale": {
      "x": 1,
      "y": 1,
      "z": 1
    }
  },
  {
    "position": {
      "x": 594.63407597026,
      "y": -60.45740714365667,
      "z": -44.64004769690018
    },
    "rotation": {
      "x": 0,
      "y": -2.9999999998658877,
      "z": 0
    },
    "scale": {
      "x": 1,
      "y": 1,
      "z": 1
    }
  },
  {
    "position": {
      "x": 595.2422296946133,
      "y": -66.20479517204706,
      "z": -22.219518645480775
    },
    "rotation": {
      "x": 0,
      "y": -3.184349999874829,
      "z": 0
    },
    "scale": {
      "x": 1,
      "y": 1,
      "z": 1
    }
  },
  {
    "position": {
      "x": 594.6536404167573,
      "y": -69.66923490206617,
      "z": -8.462103820379298
    },
    "rotation": {
      "x": 0,
      "y": -3.184349999874829,
      "z": 0
    },
    "scale": {
      "x": 1,
      "y": 1,
      "z": 1
    }
  },
  {
    "position": {
      "x": 594.119336424525,
      "y": -72.81415114203025,
      "z": 4.026471728644992
    },
    "rotation": {
      "x": 0,
      "y": -3.184349999874829,
      "z": 0
    },
    "scale": {
      "x": 1,
      "y": 1,
      "z": 1
    }
  },
  {
    "position": {
      "x": 592.9542277527194,
      "y": -75.9150952907072,
      "z": 16.502581173401268
    },
    "rotation": {
      "x": 0,
      "y": -3.359549999848006,
      "z": 0
    },
    "scale": {
      "x": 1,
      "y": 1,
      "z": 1
    }
  },
  {
    "position": {
      "x": 589.3513957114039,
      "y": -78.37613851363378,
      "z": 27.084523158285037
    },
    "rotation": {
      "x": 0,
      "y": -3.5249999998658876,
      "z": 0
    },
    "scale": {
      "x": 1,
      "y": 1,
      "z": 1
    }
  },
  {
    "position": {
      "x": 585.6105697905575,
      "y": -80.49525536276656,
      "z": 36.35847708472579
    },
    "rotation": {
      "x": 0,
      "y": -3.5375999998748284,
      "z": 0
    },
    "scale": {
      "x": 1,
      "y": 1,
      "z": 1
    }
  },
  {
    "position": {
      "x": 579.4680315513551,
      "y": -82.86227269714954,
      "z": 47.2162887923314
    },
    "rotation": {
      "x": 0,
      "y": -3.689999999865888,
      "z": 0
    },
    "scale": {
      "x": 1,
      "y": 1,
      "z": 1
    }
  },
  {
    "position": {
      "x": 572.9436017419739,
      "y": -85.15924283142266,
      "z": 57.896037883007466
    },
    "rotation": {
      "x": 0,
      "y": -3.689999999865888,
      "z": 0
    },
    "scale": {
      "x": 1,
      "y": 1,
      "z": 1
    }
  },
  {
    "position": {
      "x": 565.5995167927742,
      "y": -87.11627803072003,
      "z": 67.45029205032574
    },
    "rotation": {
      "x": 0,
      "y": -3.8531999998390662,
      "z": 0
    },
    "scale": {
      "x": 1,
      "y": 1,
      "z": 1
    }
  },
  {
    "position": {
      "x": 556.7659848885075,
      "y": -88.79772130134387,
      "z": 76.30064756098
    },
    "rotation": {
      "x": 0,
      "y": -3.990749999865889,
      "z": 0
    },
    "scale": {
      "x": 1,
      "y": 1,
      "z": 1
    }
  },
  {
    "position": {
      "x": 549.3672045422863,
      "y": -89.70609186572455,
      "z": 81.74961679870512
    },
    "rotation": {
      "x": 0,
      "y": -4.102949999883769,
      "z": 0
    },
    "scale": {
      "x": 1,
      "y": 1,
      "z": 1
    }
  },
  {
    "position": {
      "x": 538.408315132581,
      "y": -90.94464955888688,
      "z": 89.39984345688299
    },
    "rotation": {
      "x": 0,
      "y": -4.102949999883769,
      "z": 0
    },
    "scale": {
      "x": 1,
      "y": 1,
      "z": 1
    }
  },
  {
    "position": {
      "x": 521.8050895864378,
      "y": -92.0797366534465,
      "z": 98.0759109922974
    },
    "rotation": {
      "x": 0,
      "y": -4.252349999874828,
      "z": 0
    },
    "scale": {
      "x": 1,
      "y": 1,
      "z": 1
    }
  },
  {
    "position": {
      "x": 509.4216524571875,
      "y": -92.48941415152174,
      "z": 102.82809135362618
    },
    "rotation": {
      "x": 0,
      "y": -4.425449999839064,
      "z": 0
    },
    "scale": {
      "x": 1,
      "y": 1,
      "z": 1
    }
  },
  {
    "position": {
      "x": 490.2319928387833,
      "y": -91.23125794591007,
      "z": 107.04336209042049
    },
    "rotation": {
      "x": 0,
      "y": -4.501949999839064,
      "z": 0
    },
    "scale": {
      "x": 1,
      "y": 1,
      "z": 1
    }
  },
  {
    "position": {
      "x": 471.4653374668221,
      "y": -90.17122764966823,
      "z": 111.05194615117875
    },
    "rotation": {
      "x": 0,
      "y": -4.501949999839064,
      "z": 0
    },
    "scale": {
      "x": 1,
      "y": 1,
      "z": 1
    }
  },
  {
    "position": {
      "x": 448.50096789701547,
      "y": -87.98525672097267,
      "z": 114.9705607315833
    },
    "rotation": {
      "x": 0,
      "y": -4.637699999839063,
      "z": 0
    },
    "scale": {
      "x": 1,
      "y": 1,
      "z": 1
    }
  },
  {
    "position": {
      "x": 432.7200868184134,
      "y": -86.12226555112969,
      "z": 116.15141524534602
    },
    "rotation": {
      "x": 0,
      "y": -4.637699999839063,
      "z": 0
    },
    "scale": {
      "x": 1,
      "y": 1,
      "z": 1
    }
  },
  {
    "position": {
      "x": 417.36333771469435,
      "y": -83.82608304685806,
      "z": 115.25401958391626
    },
    "rotation": {
      "x": 0,
      "y": -4.838399999856944,
      "z": 0
    },
    "scale": {
      "x": 1,
      "y": 1,
      "z": 1
    }
  },
  {
    "position": {
      "x": 398.33045343972753,
      "y": -80.51388159479242,
      "z": 112.84289097838041
    },
    "rotation": {
      "x": 0,
      "y": -4.838399999856944,
      "z": 0
    },
    "scale": {
      "x": 1,
      "y": 1,
      "z": 1
    }
  }
]